[{"place_id": 42729671, "licence": "Data \u00a9 OpenStreetMap contributors, ODbL 1.0. http://osm.org/copyright", "osm_type": "way", "osm_id": 280293524, "lat": "31.7972558", "lon": "35.2237710", "class": "highway", "type": "residential", "place_rank": 26, "importance": 0.05341538796063169, "addresstype": "road", "name": "Mikve Yisrael", "display_name": "Mikve Yisrael, Maalot Dafna, West Jerusalem, Jerusalem Subdistrict, Jerusalem District, 9711769, Israel", "boundingbox": ["31.7964921", "31.7978642", "35.2231761", "35.2241459"], "geojson": {"type": "LineString", "coordinates": [[35.2241459, 31.7964921], [35.2240614, 31.7967287], [35.2239326, 31.7969977], [35.2238254, 31.7971844], [35.2236667, 31.7973925], [35.2235545, 31.7975117], [35.2234353, 31.7976381], [35.2233507, 31.7977278], [35.2232595, 31.797806], [35.2231761, 31.7978642]]}}, {"place_id": 43165535, "licence": "Data \u00a9 OpenStreetMap contributors, ODbL 1.0. http://osm.org/copyright", "osm_type": "way", "osm_id": 1248957440, "lat": "31.7978606", "lon": "35.2230353", "class": "highway", "type": "residential", "place_rank": 26, "importance": 0.05341538796063169, "addresstype": "road", "name": "Mikve Yisrael", "display_name": "Mikve Yisrael, Sanhedriyya, West Jerusalem, Jerusalem Subdistrict, Jerusalem District, 9711769, Israel", "boundingbox": ["31.7978061", "31.7978692", "35.2229059", "35.2231761"], "geojson": {"type": "LineString", "coordinates": [[35.2229059, 31.7978061], [35.2229525, 31.7978348], [35.2229922, 31.7978497], [35.2230349, 31.7978605], [35.223071, 31.7978667], [35.2231179, 31.7978692], [35.2231761, 31.7978642]]}}, {"place_id": 42940726, "licence": "Data \u00a9 OpenStreetMap contributors, ODbL 1.0. http://osm.org/copyright", "osm_type": "way", "osm_id": 1248957439, "lat": "31.7979086", "lon": "35.2230883", "class": "highway", "type": "residential", "place_rank": 26, "importance": 0.05341538796063169, "addresstype": "road", "name": "Mikve Yisrael", "display_name": "Mikve Yisrael, Sanhedriyya, West Jerusalem, Jerusalem Subdistrict, Jerusalem District, 9711769, Israel", "boundingbox": ["31.7978642", "31.7979531", "35.2230005", "35.2231761"], "geojson": {"type": "LineString", "coordinates": [[35.2231761, 31.7978642], [35.2230692, 31.7979183], [35.2230005, 31.7979531]]}}, {"place_id": 195480960, "licence": "Data \u00a9 OpenStreetMap contributors, ODbL 1.0. http://osm.org/copyright", "osm_type": "way", "osm_id": 58732111, "lat": "32.0282452", "lon": "34.7775689", "class": "highway", "type": "secondary", "place_rank": 26, "importance": 0.053408333714808846, "addresstype": "road", "name": "Mikve Israel", "display_name": "Mikve Israel, Agrobank, Shikun Amami, Holon, Tel Aviv Subdistrict, Tel-Aviv District, 5829212, Israel", "boundingbox": ["32.0279830", "32.0285474", "34.7758869", "34.7792679"], "geojson": {"type": "LineString", "coordinates": [[34.7758869, 32.0285474], [34.7760001, 32.0284771], [34.7766753, 32.0283803], [34.7770325, 32.028328], [34.7781788, 32.0281511], [34.7787592, 32.0280615], [34.7792679, 32.027983]]}}, {"place_id": 195451282, "licence": "Data \u00a9 OpenStreetMap contributors, ODbL 1.0. http://osm.org/copyright", "osm_type": "way", "osm_id": 58732112, "lat": "32.0283580", "lon": "34.7775302", "class": "highway", "type": "secondary", "place_rank": 26, "importance": 0.053408333714808846, "addresstype": "road", "name": "Mikve Israel", "display_name": "Mikve Israel, Agrobank, Shikun Amami, Holon, Tel Aviv Subdistrict, Tel-Aviv District, 5829212, Israel", "boundingbox": ["32.0281111", "32.0285760", "34.7758869", "34.7791738"], "geojson": {"type": "LineString", "coordinates": [[34.7791738, 32.0281111], [34.7771912, 32.0284089], [34.776022, 32.028576], [34.7758869, 32.0285474]]}}, {"place_id": 195336715, "licence": "Data \u00a9 OpenStreetMap contributors, ODbL 1.0. http://osm.org/copyright", "osm_type": "way", "osm_id": 109814523, "lat": "32.0278992", "lon": "34.7804729", "class": "highway", "type": "secondary", "place_rank": 26, "importance": 0.053408333714808846, "addresstype": "road", "name": "Mikve Israel", "display_name": "Mikve Israel, Agrobank, Shikun Amami, Holon, Tel Aviv Subdistrict, Tel-Aviv District, 5829212, Israel", "boundingbox": ["32.0276819", "32.0281111", "34.7791738", "34.7817710"], "geojson": {"type": "LineString", "coordinates": [[34.781771, 32.0276819], [34.7812745, 32.0277684], [34.7791738, 32.0281111]]}}, {"place_id": 194660090, "licence": "Data \u00a9 OpenStreetMap contributors, ODbL 1.0. http://osm.org/copyright", "osm_type": "way", "osm_id": 51324650, "lat": "32.0277844", "lon": "34.7805106", "class": "highway", "type": "secondary", "place_rank": 26, "importance": 0.053408333714808846, "addresstype": "road", "name": "Mikve Israel", "display_name": "Mikve Israel, Agrobank, Shikun Amami, Holon, Tel Aviv Subdistrict, Tel-Aviv District, 5829212, Israel", "boundingbox": ["32.0275529", "32.0279830", "34.7792679", "34.7817474"], "geojson": {"type": "LineString", "coordinates": [[34.7792679, 32.027983], [34.7795782, 32.0279324], [34.7809802, 32.0277098], [34.7814404, 32.027618], [34.7817474, 32.0275529]]}}, {"place_id": 195547802, "licence": "Data \u00a9 OpenStreetMap contributors, ODbL 1.0. http://osm.org/copyright", "osm_type": "way", "osm_id": 832211738, "lat": "32.0626211", "lon": "34.7757863", "class": "highway", "type": "residential", "place_rank": 26, "importance": 0.053408333714808846, "addresstype": "road", "name": "Mikve Israel", "display_name": "Mikve Israel, Lev Tel Aviv, Tel Aviv, Tel-Aviv, Tel Aviv Subdistrict, Tel-Aviv District, 6511604, Israel", "boundingbox": ["32.0624188", "32.0627744", "34.7751009", "34.7764837"], "geojson": {"type": "LineString", "coordinates": [[34.7751009, 32.0624188], [34.7751192, 32.0624332], [34.7751373, 32.0624422], [34.7751573, 32.0624496], [34.77551, 32.0625445], [34.7756202, 32.0625759], [34.7758531, 32.0626393], [34.7762243, 32.0627413], [34.7763097, 32.0627614], [34.7763717, 32.0627713], [34.7764837, 32.0627744]]}}, {"place_id": 195823539, "licence": "Data \u00a9 OpenStreetMap contributors, ODbL 1.0. http://osm.org/copyright", "osm_type": "way", "osm_id": 362452232, "lat": "32.0627244", "lon": "34.7774956", "class": "highway", "type": "residential", "place_rank": 26, "importance": 0.053408333714808846, "addresstype": "road", "name": "Mikve Israel", "display_name": "Mikve Israel, Lev Tel Aviv, Tel Aviv, Tel-Aviv, Tel Aviv Subdistrict, Tel-Aviv District, 6511604, Israel", "boundingbox": ["32.0627016", "32.0627491", "34.7771301", "34.7778612"], "geojson": {"type": "LineString", "coordinates": [[34.7771301, 32.0627491], [34.777413, 32.0627289], [34.777593, 32.0627192], [34.777725, 32.0627104], [34.7778612, 32.0627016]]}}, {"place_id": 193974459, "licence": "Data \u00a9 OpenStreetMap contributors, ODbL 1.0. http://osm.org/copyright", "osm_type": "way", "osm_id": 1035607027, "lat": "32.0627646", "lon": "34.7768070", "class": "highway", "type": "residential", "place_rank": 26, "importance": 0.053408333714808846, "addresstype": "road", "name": "Mikve Israel", "display_name": "Mikve Israel, Lev Tel Aviv, Tel Aviv, Tel-Aviv, Tel Aviv Subdistrict, Tel-Aviv District, 6511604, Israel", "boundingbox": ["32.0627491", "32.0627744", "34.7764837", "34.7771301"], "geojson": {"type": "LineString", "coordinates": [[34.7764837, 32.0627744], [34.7767553, 32.0627671], [34.7771301, 32.0627491]]}}, {"place_id": 194799698, "licence": "Data \u00a9 OpenStreetMap contributors, ODbL 1.0. http://osm.org/copyright", "osm_type": "way", "osm_id": 719605215, "lat": "32.0626941", "lon": "34.7780441", "class": "highway", "type": "residential", "place_rank": 26, "importance": 0.053408333714808846, "addresstype": "road", "name": "Mikve Israel", "display_name": "Mikve Israel, Lev Tel Aviv, Tel Aviv, Tel-Aviv, Tel Aviv Subdistrict, Tel-Aviv District, 6511604, Israel", "boundingbox": ["32.0626867", "32.0627016", "34.7778612", "34.7782270"], "geojson": {"type": "LineString", "coordinates": [[34.7778612, 32.0627016], [34.778227, 32.0626867]]}}, {"place_id": 194174278, "licence": "Data \u00a9 OpenStreetMap contributors, ODbL 1.0. http://osm.org/copyright", "osm_type": "way", "osm_id": 719605213, "lat": "32.0626805", "lon": "34.7783294", "class": "highway", "type": "residential", "place_rank": 26, "importance": 0.053408333714808846, "addresstype": "road", "name": "Mikve Israel", "display_name": "Mikve Israel, Lev Tel Aviv, Tel Aviv, Tel-Aviv, Tel Aviv Subdistrict, Tel-Aviv District, 6511604, Israel", "boundingbox": ["32.0626683", "32.0626867", "34.7782270", "34.7784313"], "geojson": {"type": "LineString", "coordinates": [[34.778227, 32.0626867], [34.7783334, 32.0626803], [34.7784313, 32.0626683]]}}, {"place_id": 42564347, "licence": "Data \u00a9 OpenStreetMap contributors, ODbL 1.0. http://osm.org/copyright", "osm_type": "way", "osm_id": 112173899, "lat": "31.7799510", "lon": "34.6614225", "class": "highway", "type": "living_street", "place_rank": 26, "importance": 0.053400354772259066, "addresstype": "road", "name": "Mikve Yisra'el", "display_name": "Mikve Yisra'el, \u05e8\u05d5\u05d1\u05e2 \u05d8\u05f3, Ashdod, Ashkelon Subdistrict, South District, 7757403, Israel", "boundingbox": ["31.7794530", "31.7809715", "34.6614071", "34.6624476"], "geojson": {"type": "LineString", "coordinates": [[34.6624476, 31.779453], [34.6621158, 31.7796082], [34.6614071, 31.7799238], [34.6619709, 31.7809165], [34.6619794, 31.7809318], [34.6620015, 31.7809715]]}}, {"place_id": 43190093, "licence": "Data \u00a9 OpenStreetMap contributors, ODbL 1.0. http://osm.org/copyright", "osm_type": "way", "osm_id": 1036013651, "lat": "31.7798197", "lon": "34.6613494", "class": "highway", "type": "living_street", "place_rank": 26, "importance": 0.053400354772259066, "addresstype": "road", "name": "Mikve Yisra'el", "display_name": "Mikve Yisra'el, \u05e8\u05d5\u05d1\u05e2 \u05d8\u05f3, Ashdod, Ashkelon Subdistrict, South District, 7757403, Israel", "boundingbox": ["31.7797156", "31.7799238", "34.6612917", "34.6614071"], "geojson": {"type": "LineString", "coordinates": [[34.6614071, 31.7799238], [34.6612917, 31.7797156]]}}, {"place_id": 406292978, "licence": "Data \u00a9 OpenStreetMap contributors, ODbL 1.0. http://osm.org/copyright", "osm_type": "way", "osm_id": 1384337487, "lat": "32.0287438", "lon": "34.7749540", "class": "highway", "type": "secondary_link", "place_rank": 27, "importance": 0.04007500038147554, "addresstype": "road", "name": "Mikve Israel", "display_name": "Mikve Israel, Agrobank, Shikun Amami, Holon, Tel Aviv Subdistrict, Tel-Aviv District, 5822304, Israel", "boundingbox": ["32.0285760", "32.0290002", "34.7739196", "34.7760220"], "geojson": {"type": "LineString", "coordinates": [[34.776022, 32.028576], [34.7757072, 32.0286223], [34.7744952, 32.0288178], [34.7743072, 32.028847], [34.7740712, 32.0288973], [34.7739828, 32.0289422], [34.7739196, 32.0290002]]}}, {"place_id": 406292979, "licence": "Data \u00a9 OpenStreetMap contributors, ODbL 1.0. http://osm.org/copyright", "osm_type": "way", "osm_id": 1384337488, "lat": "32.0286155", "lon": "34.7749319", "class": "highway", "type": "secondary_link", "place_rank": 27, "importance": 0.04007500038147554, "addresstype": "road", "name": "Mikve Israel", "display_name": "Mikve Israel, Agrobank, Shikun Amami, Holon, Tel Aviv Subdistrict, Tel-Aviv District, 5822304, Israel", "boundingbox": ["32.0284771", "32.0287163", "34.7738637", "34.7760001"], "geojson": {"type": "LineString", "coordinates": [[34.7738637, 32.0286878], [34.7739479, 32.0287086], [34.7740189, 32.028715], [34.7740874, 32.0287163], [34.7743843, 32.0286913], [34.7750617, 32.0285975], [34.7750962, 32.0285927], [34.7751948, 32.0285791], [34.775216, 32.0285761], [34.7754774, 32.02854], [34.7757296, 32.028505], [34.7760001, 32.0284771]]}}, {"place_id": 42959094, "licence": "Data \u00a9 OpenStreetMap contributors, ODbL 1.0. http://osm.org/copyright", "osm_type": "way", "osm_id": 280293516, "lat": "31.7983281", "lon": "35.2236453", "class": "highway", "type": "residential", "place_rank": 26, "importance": 0.05341538796063169, "addresstype": "road", "name": "Mikve Yisrael", "display_name": "Mikve Yisrael, Ramat Eshkol, West Jerusalem, Jerusalem Subdistrict, Jerusalem District, 9711769, Israel", "boundingbox": ["31.7978642", "31.7986835", "35.2231761", "35.2241994"], "geojson": {"type": "LineString", "coordinates": [[35.2231761, 31.7978642], [35.2232199, 31.7979115], [35.2233391, 31.79804], [35.2235336, 31.7982319], [35.2235625, 31.7982604], [35.223702, 31.7983744], [35.2238176, 31.798463], [35.2238487, 31.7984868], [35.2239935, 31.798578], [35.2241994, 31.7986835]]}}]